pyrdmp/__init__.py
pyrdmp/dmp.py
pyrdmp/plots.py
pyrdmp/utils.py
pyrdmp-0.2.2.dist-info/LICENSE
pyrdmp-0.2.2.dist-info/METADATA
pyrdmp-0.2.2.dist-info/WHEEL
pyrdmp-0.2.2.dist-info/top_level.txt
pyrdmp-0.2.2.dist-info/RECORD
