Metadata-Version: 2.1
Name: pyrdmp
Version: 0.2.2
Summary: Python Library for Reinforced Dynamic Movement Primitives
Home-page: https://github.com/Heracleia/pyrdmp
Author: Michail Theofanidis, Joe Cloud, James Brady
Author-email: git@joe.cloud
License: GNU GENERAL PUBLIC LICENSE
Requires-Dist: matplotlib (==2.2.3)
Requires-Dist: numpy (==1.16.0)
